frugy/__init__.py
frugy/__main__.py
frugy/areas.py
frugy/cli.py
frugy/fru.py
frugy/fru_registry.py
frugy/multirecords.py
frugy/multirecords_fmc.py
frugy/multirecords_ipmi.py
frugy/multirecords_picmg.py
frugy/multirecords_xilinx.py
frugy/types.py
frugy-0.5.1.dist-info/licenses/LICENSE.txt
frugy-0.5.1.dist-info/METADATA
frugy-0.5.1.dist-info/WHEEL
frugy-0.5.1.dist-info/entry_points.txt
frugy-0.5.1.dist-info/top_level.txt
frugy-0.5.1.dist-info/RECORD
