Metadata-Version: 2.4
Name: frugy
Version: 0.5.1
Summary: FRU Generator YAML
Home-page: https://techlab.desy.de
Author: Patrick Huesmann
Author-email: patrick.huesmann@desy.de
License: BSD
Keywords: ipmi fru microtca amc fmc picmg vita
Classifier: Programming Language :: Python :: 3.6
Classifier: Operating System :: OS Independent
Classifier: Environment :: Console
Classifier: License :: OSI Approved :: BSD License
Classifier: Intended Audience :: Developers
Classifier: Development Status :: 3 - Alpha
Requires-Python: >=3.6
License-File: LICENSE.txt
Requires-Dist: bitstruct>=8.0.0
Requires-Dist: PyYAML>=5.1.0
Requires-Dist: bidict>=0.20.0
Requires-Dist: macaddress>=2.0.2
Dynamic: author
Dynamic: author-email
Dynamic: classifier
Dynamic: description
Dynamic: description-content-type
Dynamic: home-page
Dynamic: keywords
Dynamic: license
Dynamic: license-file
Dynamic: requires-dist
Dynamic: requires-python
Dynamic: summary
